setup.py
bin/ex47.py
ex47/__init__.py
projectname.egg-info/PKG-INFO
projectname.egg-info/SOURCES.txt
projectname.egg-info/dependency_links.txt
projectname.egg-info/requires.txt
projectname.egg-info/top_level.txt