Metadata-Version: 1.0
Name: projectname
Version: 0.1.1
Summary: My Project
Home-page: UNKNOWN
Author: Andrew Kitchell
Author-email: akitchell@gmail.com
License: UNKNOWN
Platform: UNKNOWN
